h5pPlugin_package/__init__.py
h5pPlugin_package/iframe.py
h5pPlugin-0.0.5.dist-info/LICENCE
h5pPlugin-0.0.5.dist-info/METADATA
h5pPlugin-0.0.5.dist-info/WHEEL
h5pPlugin-0.0.5.dist-info/top_level.txt
h5pPlugin-0.0.5.dist-info/RECORD
