Metadata-Version: 2.1
Name: h5pPlugin
Version: 0.0.5
Summary: H5P package
Home-page: https://github.com/pypa/sampleproject
Author: Rasmus Janson
Author-email: jansonrasmus@gmail.com
License: UNKNOWN
Project-URL: Bug Tracker, https://github.com/pypa/sampleproject/issues
Platform: UNKNOWN
Classifier: Programming Language :: Python :: 3
Classifier: License :: OSI Approved :: MIT License
Classifier: Operating System :: OS Independent
Requires-Python: >=3.6
License-File: LICENCE
